Metadata-Version: 1.0
Name: adevinta-yapo-bi-read-params
Version: 0.0.0.0.11
Summary: Class develop that enable read input params by command line.
Home-page: https://github.mpi-internal.com/Yapo/bi-insights
Author: Yapo BI
Author-email: bi.insights@yapo.cl
License: MIT
Platform: UNKNOWN
